{
  "batch": "20260223-095746",
  "generatedAt": "2026-02-23T10:06:16.419Z",
  "requestedApply": true,
  "autoApplyEnabled": true,
  "totalCandidates": 16,
  "publishableCount": 0,
  "appliedCount": 0,
  "rejectedCount": 16,
  "reasonsHistogram": {
    "decision_not_candidate_ready": 16,
    "candidate_type_not_auto_publishable": 16,
    "source_url_already_used": 16,
    "linked_existing_entry": 16,
    "suggested_entry_incomplete": 16,
    "entry_source_url_already_exists": 16,
    "confidence_too_low": 10
  }
}
